aicat/AnnoCross.py
aicat/AnnoGroup.py
aicat/AnnoSingle.py
aicat/__init__.py
aicat/agent.py
aicat/annotation.py
aicat/cli_indepth.py
aicat/cli_scoring.py
aicat/cli_subcluster.py
aicat/flow.py
aicat/main_indepth.py
aicat/main_scoring.py
aicat/main_subcluster.py
aicat/steps.py
aicat/utils.py
aicat_annotator-0.0.1.dist-info/METADATA
aicat_annotator-0.0.1.dist-info/WHEEL
aicat_annotator-0.0.1.dist-info/entry_points.txt
aicat_annotator-0.0.1.dist-info/licenses/LICENSE
aicat_annotator-0.0.1.dist-info/RECORD
