Metadata-Version: 2.4
Name: aicat-annotator
Version: 0.0.1
Summary: Agentic-AI Cell-type Annotation Tool
Project-URL: Homepage, https://github.com/RavenGan/AICAT
Project-URL: Issues, https://github.com/RavenGan/AICAT/issues
Author-email: Dailin Gan <dailin.raven.gan@gmail.com>, Jun Li <jun.li@nd.edu>
License-Expression: MIT
License-File: LICENSE
Classifier: License :: OSI Approved :: MIT License
Classifier: Operating System :: OS Independent
Classifier: Programming Language :: Python :: 3
Requires-Python: >=3.10
Requires-Dist: argparse
Requires-Dist: charset-normalizer<3
Requires-Dist: langchain-core>=0.1.36
Requires-Dist: langchain-openai==0.1.7
Requires-Dist: langchain==0.1.20
Requires-Dist: leidenalg>=0.10.1
Requires-Dist: pandas>=2.2.3
Requires-Dist: pydantic-settings>=2.2.1
Requires-Dist: pydantic>=2.10.6
Requires-Dist: python-dotenv>=1.0.1
Requires-Dist: python-igraph>=0.11.5
Requires-Dist: requests<2.32
Requires-Dist: scanpy>=1.11.0
Requires-Dist: urllib3<2.1
Provides-Extra: dev
Requires-Dist: black; extra == 'dev'
Requires-Dist: isort; extra == 'dev'
Requires-Dist: pytest; extra == 'dev'
